easyQuake/__init__.py
easyQuake/easyQuake.py
easyQuake/EQTransformer/EqT_model.h5
easyQuake/EQTransformer/EqT_model2.h5
easyQuake/EQTransformer/EqT_utils.py
easyQuake/EQTransformer/__init__.py
easyQuake/EQTransformer/mseed_predictor.py
easyQuake/gpd_predict/__init__.py
easyQuake/gpd_predict/gpd_predict.py
easyQuake/gpd_predict/model_pol.json
easyQuake/gpd_predict/model_pol_best.hdf5
easyQuake/hyp2000/__init__.py
easyQuake/hyp2000/standard.crh
easyQuake/phasenet/__init__.py
easyQuake/phasenet/data_reader.py
easyQuake/phasenet/detect_peaks.py
easyQuake/phasenet/model.py
easyQuake/phasenet/phasenet_predict.py
easyQuake/phasenet/postprocess.py
easyQuake/phasenet/model/190703-214543/checkpoint
easyQuake/phasenet/model/190703-214543/config.log
easyQuake/phasenet/model/190703-214543/loss.log
easyQuake/phasenet/model/190703-214543/model_95.ckpt.data-00000-of-00001
easyQuake/phasenet/model/190703-214543/model_95.ckpt.index
easyQuake/phasenet/model/190703-214543/model_95.ckpt.meta
easyQuake/phasepapy/__init__.py
easyQuake/phasepapy/assoc1D.py
easyQuake/phasepapy/cf_fb.py
easyQuake/phasepapy/fbpicker.py
easyQuake/phasepapy/func1D.py
easyQuake/phasepapy/scnl.py
easyQuake/phasepapy/tables1D.py
easyQuake/phasepapy/tt_stations_1D.py
easyQuake/phasepapy/util.py
easyQuake/seisbench/__init__.py
easyQuake/seisbench/aepicker.py
easyQuake/seisbench/annotations.py
easyQuake/seisbench/base.py
easyQuake/seisbench/decorators.py
easyQuake/seisbench/eqtransformer.py
easyQuake/seisbench/file.py
easyQuake/seisbench/files.py
easyQuake/seisbench/gpd.py
easyQuake/seisbench/phasenet.py
easyQuake/seisbench/region.py
easyQuake/seisbench/run_seisbench.py
easyQuake/seisbench/torch_helpers.py
easyQuake/seisbench/trace_ops.py
easyQuake/sta_lta/__init__.py
easyQuake/sta_lta/trigger_p_s.py
easyQuake-1.4.0.dist-info/LICENSE
easyQuake-1.4.0.dist-info/METADATA
easyQuake-1.4.0.dist-info/WHEEL
easyQuake-1.4.0.dist-info/entry_points.txt
easyQuake-1.4.0.dist-info/top_level.txt
easyQuake-1.4.0.dist-info/RECORD
