Metadata-Version: 2.1
Name: easyQuake
Version: 1.4.0
Summary: Simplified machine-learning driven earthquake detection, location, and analysis
Home-page: https://github.com/jakewalter/easyQuake
Author: Jake Walter
Author-email: jakeiwalter@gmail.com
Classifier: Programming Language :: Python :: 3
Classifier: License :: OSI Approved :: MIT License
Classifier: Operating System :: OS Independent
Requires-Python: >=3.7, <=3.8
License-File: LICENSE
Requires-Dist: basemap
Requires-Dist: keras (==2.3.1)
Requires-Dist: obspy
Requires-Dist: pandas
Requires-Dist: tensorflow (==2.2)
Requires-Dist: h5py (==2.10.0)
Requires-Dist: tqdm
Requires-Dist: tensorflow-gpu (==2.2)
Requires-Dist: protobuf (==3.20.*)
Requires-Dist: torch (==1.7.1)
Requires-Dist: torchmetrics (==0.8.0)
Requires-Dist: torchvision (==0.8.2)
